tests/__init__.py
vlab_mgr/__init__.py
vlab_mgr/vlab_mgr.py
vlab_mgr/lib/__init__.py
vlab_mgr-0.0.1.dist-info/LICENSE
vlab_mgr-0.0.1.dist-info/METADATA
vlab_mgr-0.0.1.dist-info/WHEEL
vlab_mgr-0.0.1.dist-info/entry_points.txt
vlab_mgr-0.0.1.dist-info/top_level.txt
vlab_mgr-0.0.1.dist-info/RECORD
