Metadata-Version: 2.1
Name: vlab-mgr
Version: 0.0.1
Summary: CLI for administrating a vLab server
Home-page: UNKNOWN
Author: Nicholas Willhite
Author-email: UNKNOWN
License: UNKNOWN
Platform: UNKNOWN
Classifier: Development Status :: 3 - Alpha
Classifier: Intended Audience :: System Administrators
Classifier: License :: OSI Approved :: Apache Software License
Classifier: Natural Language :: English
Classifier: Programming Language :: Python :: 3.5
Requires-Dist: click
Requires-Dist: pyyaml
